{
    "status": "ok",
    "totalResults": 38,
    "articles": [
        {
            "source": {
                "id": "the-times-of-india",
                "name": "The Times of India"
            },
            "author": "AP",
            "title": "A small spacewalk demonstrates a quantum leap in China's extraterrestrial ambitions - ​China's ET ambitions - Economic Times",
            "description": "According to an AFP report, astronauts at China's new space station conducted their first spacewalk July 4, state media reported, as Beijing presses on with its extraterrestrial ambitions. It was only the second time the country's astronauts have stepped out …",
            "url": "https://economictimes.indiatimes.com/news/science/a-small-spacewalk-demonstrates-a-quantum-leap-in-chinas-extraterrestrial-ambitions/chinas-et-ambitions/slideshow/84137094.cms",
            "urlToImage": "https://img.etimg.com/thumb/msid-84137094,width-1070,height-580,overlay-economictimes/photo.jpg",
            "publishedAt": "2021-07-05T08:11:00Z",
            "content": "05 Jul 2021, 01:41 PM IST\r\nAccording to an AFP report, astronauts at China's new space station conducted their first spacewalk July 4, state media reported, as Beijing presses on with its extraterres… [+1277 chars]"
        },
        {
            "source": {
                "id": null,
                "name": "Philippine Star"
            },
            "author": "Ramon Royandoyan",
            "title": "Petron to sell P50 billion of bonds to pay old debts - Philstar.com",
            "description": "Oil giant Petron Corp. announced Monday its plan to tap the debt market anew to raise funds to pay maturing liabilities.",
            "url": "https://www.philstar.com/business/2021/07/05/2110345/petron-sell-p50-billion-bonds-pay-old-debts",
            "urlToImage": "https://media.philstar.com/images/articles/petron_2018-08-08_17-22-58.jpg",
            "publishedAt": "2021-07-05T08:09:00Z",
            "content": "MANILA, Philippines — Oil giant Petron Corp. announced Monday its plan to tap the debt market anew to raise funds to pay maturing liabilities.\r\nIn a disclosure to the stock exchange, Petron said it w… [+1600 chars]"
        },
        {
            "source": {
                "id": null,
                "name": "ScienceAlert"
            },
            "author": "Michelle Starr",
            "title": "Astronomers Detect a Lurking Cosmic Cloud, Bigger Than The Entire Milky Way - ScienceAlert",
            "description": "In the yawning vacuum of intergalactic space, something large is lurking.",
            "url": "https://www.sciencealert.com/a-mysterious-cloud-of-gas-bigger-than-the-milky-way-is-just-hanging-out-in-space",
            "urlToImage": "https://www.sciencealert.com/images/2021-07/processed/lonely-cloud_1024.jpg",
            "publishedAt": "2021-07-05T07:00:19Z",
            "content": "In the yawning vacuum of intergalactic space, something large is lurking.\r\nNot a galaxy, although it's of a comparable size: A vast cloud of hot, faintly glowing gas, bigger than the Milky Way, in th… [+4524 chars]"
        },
        {
            "source": {
                "id": "google-news",
                "name": "Google News"
            },
            "author": null,
            "title": "Germany - Brazil | Finals | Full Highlights - FIBA Olympic Qualifying Tournament 2020 - FIBA - The Basketball Channel",
            "description": null,
            "url": "https://news.google.com/__i/rss/rd/articles/CBMiK2h0dHBzOi8vd3d3LnlvdXR1YmUuY29tL3dhdGNoP3Y9ZmJvakU3Z0I1d0HSAQA?oc=5",
            "urlToImage": null,
            "publishedAt": "2021-07-05T07:00:09Z",
            "content": null
        },
        {
            "source": {
                "id": null,
                "name": "Mb.com.ph"
            },
            "author": null,
            "title": "Alex Gongaza graces the cover of Harper's Bazaar Vietnam magazine - Manila Bulletin",
            "description": "Alex talks about her journey from being an actress to dominating YouTube and finding love \nAlex Gonzaga on the cover of Harper's Bazaar Vietnam magazine July 2021 issue\n  Alex Gonzaga can now be seen on the newsstands abroad as she graces the cover of Harper'…",
            "url": "https://mb.com.ph/2021/07/05/alex-gongaza-graces-the-cover-of-harpers-bazaar-vietnam-magazine/",
            "urlToImage": "https://mb.com.ph/wp-content/uploads/2021/07/15793.jpeg",
            "publishedAt": "2021-07-05T06:39:00Z",
            "content": "Alex Gonzaga can now be seen on the newsstands abroad as she graces the cover of Harper’s Bazaar Vietnam magazine’s July 2021 issue. \r\nThe social media star expresses her joy through an Instagram pos… [+976 chars]"
        },
        {
            "source": {
                "id": null,
                "name": "Inquirer.net"
            },
            "author": "Cathrine Gonzales",
            "title": "Taal evacuation sites receive more test kits, anti-COVID vaccines from gov’t - INQUIRER.net",
            "description": "MANILA, Philippines — The government has distributed additional antigen test kits and will increase the COVID-19 vaccine allocation to evacuation centers that shelter residents affected by",
            "url": "https://www.inquirer.net",
            "urlToImage": "https://newsinfo.inquirer.net/files/2020/12/Screen-Shot-2020-12-11-at-2.04.58-PM-e1607666824931-620x430.png",
            "publishedAt": "2021-07-05T06:35:00Z",
            "content": "DOH Undersecretary and spokesperson Maria Rosario Vergeire. FILE PHOTO\r\nMANILA, Philippines The government has distributed additional antigen test kits and will increase the COVID-19 vaccine allocati… [+2085 chars]"
        },
        {
            "source": {
                "id": null,
                "name": "GMA News"
            },
            "author": "",
            "title": "DepEd demands public apology from World Bank over education report - GMA News Online",
            "description": "Education Secretary Leonor Briones slammed the World Bank for allegedly making conclusions based on old data, not taking into account the recent initiatives on education reform, and failing to give the Philippine government a heads-up about the report.",
            "url": "https://www.gmanetwork.com/news/news/nation/794097/deped-demands-public-apology-from-world-bank-over-education-report/story/",
            "urlToImage": "https://images.gmanews.tv/webpics/2020/07/leonor_briones_2020_07_15_23_03_44.jpg",
            "publishedAt": "2021-07-05T06:11:14Z",
            "content": "The Department of Education (DepEd) on Monday demanded a public apology from the World Bank for allegedly insulting the country after claiming that more than 80% of Filipino students do not know what… [+1377 chars]"
        },
        {
            "source": {
                "id": null,
                "name": "Rappler"
            },
            "author": "Delfin Dioquino",
            "title": "Javi Gomez de Liaño joins brother Juan in Japan, signs with Ibaraki Robots - Rappler",
            "description": "Japan has emerged as a top destination for some of the best young players in the country since Thirdy Ravena signed with the San-En NeoPhoenix",
            "url": "https://www.rappler.com/sports/javi-gomez-de-liano-joins-brother-juan-japan-signs-ibaraki-robots?fbclid=IwAR0Kvhh07xCO1SL_HeokPyOgeYNmSgxt7dxyZR_phRPuxRG7SSf_GhprMw0",
            "urlToImage": "https://assets2.rappler.com/2021/06/javi-gomez-de-liano-gilas-pilipinas-1625432930813.jpeg",
            "publishedAt": "2021-07-05T06:11:00Z",
            "content": "Ibaraki, which has been promoted to the first division after multiple years in the second division, announced the signing on Monday, July 5."
        },
        {
            "source": {
                "id": null,
                "name": "Abs-cbn.com"
            },
            "author": "Katrina Domingo, ABS-CBN News",
            "title": "DOH warns vs sulfur dioxide exposure as highest level recorded in Taal - ABS-CBN News",
            "description": "Health officials on Monday warned the public not to go near Taal Volcano after the Philippine Institute of Volcanology and Seismology (Phivolcs) said it has recorded the highest sulfur dioxide emission around the rumbling volcano over the weekend.",
            "url": "https://news.abs-cbn.com/news/07/05/21/doh-warning-sulfur-dioxide-exposure",
            "urlToImage": "https://sa.kapamilya.com/absnews/abscbnnews/media/2021/news/07/02/20210701-taal-evacuation-laurel-batangas-jc.jpg",
            "publishedAt": "2021-07-05T06:07:00Z",
            "content": "MANILA - Health officials on Monday warned the public not to go near Taal Volcano after the Philippine Institute of Volcanology and Seismology (Phivolcs) said it has recorded the highest sulfur dioxi… [+2465 chars]"
        },
        {
            "source": {
                "id": "mashable",
                "name": "Mashable"
            },
            "author": "Kellen Beck",
            "title": "On Mars, Dust Gets Everywhere And Can Ruin Everything - Mashable India",
            "description": "The red planet? More like the dust planet.",
            "url": "https://in.mashable.com/science/23289/on-mars-dust-gets-everywhere-and-can-ruin-everything",
            "urlToImage": "https://sm.mashable.com/t/mashable_in/article/o/on-mars-du/on-mars-dust-gets-everywhere-and-can-ruin-everything_z643.1200.jpg",
            "publishedAt": "2021-07-05T05:40:00Z",
            "content": "Mars is dusty. Like, really dusty. And that dust may suffocate NASAs InSight mission.\r\nInSightInSight\r\n sits on the surface of Mars measuring marsquakes and observing the local weather, powering itse… [+5685 chars]"
        },
        {
            "source": {
                "id": null,
                "name": "The Manila Times"
            },
            "author": "Agence France-Presse",
            "title": "Pope Francis undergoes colon operation – Vatican - The Manila Times",
            "description": "VATICAN CITY: Pope Francis, 84, underwent a surgery Sunday for an inflamed large colon, a Vatican statement said.The pontiff was admitted to Rome's Gemelli University...",
            "url": "https://www.manilatimes.net/2021/07/05/news/pope-francis-undergoes-colon-operation-vatican/1805815",
            "urlToImage": "https://www.manilatimes.net/manilatimes/uploads/images/2021/07/05/6710.jpg",
            "publishedAt": "2021-07-05T05:38:52Z",
            "content": "VATICAN CITY: Pope Francis, 84, underwent a surgery Sunday for an inflamed large colon, a Vatican statement said.\r\nThe pontiff was admitted to Rome's Gemelli University Hospital \"for a scheduled surg… [+1438 chars]"
        },
        {
            "source": {
                "id": null,
                "name": "GMA News"
            },
            "author": "",
            "title": "Philippines fully vaccinates over 2.8M individuals vs. COVID-19 - GMA News Online",
            "description": "The Philippines has fully vaccinated over 2.8 million people against COVID-19 as of July 4, more than four months since the launch of its inoculation campaign, the National Task Force Against COVID-19 said Monday.",
            "url": "https://www.gmanetwork.com/news/news/nation/794091/philippines-fully-vaccinates-over-2-8m-individuals-vs-covid-19/story/",
            "urlToImage": "https://images.gmanews.tv/webpics/2021/06/Vaccination_of_elderly_under_A5_group_starts_for_Baseco,_Tondo_2021_06_16_11_09_57.JPG",
            "publishedAt": "2021-07-05T05:30:33Z",
            "content": "The Philippines has fully vaccinated over 2.8 million people against COVID-19 as of July 4, more than four months since the launch of its inoculation campaign, the National Task Force Against COVID-1… [+1356 chars]"
        },
        {
            "source": {
                "id": null,
                "name": "Rappler"
            },
            "author": "Lian Buan",
            "title": "Crashed military plane not brand new but in 'tip-top' condition – AFP - Rappler",
            "description": "‘It still had around 11,000 flying hours remaining before its next maintenance,’ says military spokesman Edgard Arevalo",
            "url": "https://www.rappler.com/nation/afp-says-crashed-plane-not-brand-new-but-tip-top-condition",
            "urlToImage": "https://assets2.rappler.com/2021/07/2021-07-04T082251Z_878149076_RC2KDO9NE2ZV_RTRMADP_3_PHILIPPINE-AIRPLANE-CRASH-1625458819552.jpg",
            "publishedAt": "2021-07-05T04:45:00Z",
            "content": "The aircraft was in tip-top shape, its not brand new, but its in very good condition, said AFP spokesperson Major General Edgard Arevalo during a press conference on Monday, July 5, refuting informat… [+35 chars]"
        },
        {
            "source": {
                "id": null,
                "name": "Rappler"
            },
            "author": "Reuters",
            "title": "Mavs star Luka Doncic leads Slovenia to first Olympic basketball berth - Rappler",
            "description": "Luka Doncic sends Slovenia to the Olympics for the first time in history at the expense of Lithuania, which competed in the Games as an independent nation since 1992",
            "url": "https://www.rappler.com/sports/nba/dallas-mavericks-luka-doncic-leads-slovenia-first-olympic-basketball-berth",
            "urlToImage": "https://assets2.rappler.com/2021/07/reuters-07-05-2021-luka-doncic-1625459449143.jpg",
            "publishedAt": "2021-07-05T04:41:00Z",
            "content": "Slovenia is in Group C at the Olympics, joined by Argentina, Japan, and Spain. Donic and his teammates will open on July 26 against Argentina, whose roster includes guards Luca Vildoza of the New Yor… [+51 chars]"
        },
        {
            "source": {
                "id": null,
                "name": "Abs-cbn.com"
            },
            "author": "ABS-CBN News",
            "title": "Joyce Pring, Juancho Trivino welcome first child - ABS-CBN News",
            "description": "Joyce Pring and Juancho Triviño have welcomed their first child together.",
            "url": "https://news.abs-cbn.com/entertainment/07/05/21/joyce-pring-juancho-trivino-welcome-first-child",
            "urlToImage": "https://sa.kapamilya.com/absnews/abscbnnews/media/2021/entertainment/07/05/joyce-baby.jpg",
            "publishedAt": "2021-07-05T04:36:00Z",
            "content": "MANILA -- Joyce Pring and Juancho Triviño have welcomed their first child together.\r\nTriviño announced the wonderful news in an Instagram post on Monday where he shared a photo of his wife and newbor… [+1227 chars]"
        },
        {
            "source": {
                "id": null,
                "name": "Rappler"
            },
            "author": "Reuters",
            "title": "South Korea in talks with mRNA vaccine makers to make up to 1B doses – gov't official - Rappler",
            "description": "If agreed, the plan eases the tight global supply of COVID-19 vaccines, particularly in Asia",
            "url": "https://www.rappler.com/world/asia-pacific/south-korea-talks-mrna-vaccine-makers-up-to-1b-doses",
            "urlToImage": "https://assets2.rappler.com/2021/06/pfizer-biontech-moderna_HEALTH-CORONAVIRUS-USA-VACCINES-1625458419950.jpg",
            "publishedAt": "2021-07-05T04:17:00Z",
            "content": "The plan, if agreed, would help ease tight global supply of COVID-19 vaccines, particularly in Asia which lags North America and Europe in vaccine rollouts, and put South Korea a step closer to its a… [+54 chars]"
        },
        {
            "source": {
                "id": null,
                "name": "Autoindustriya.com"
            },
            "author": "Marcus De Guzman",
            "title": "Build your own Ford F-150 Raptor for only PHP 5,000 - Auto News - AutoIndustriya.com",
            "description": "The Blue Oval's high-performance pick-up truck will soon come in Lego Technic form",
            "url": "https://www.autoindustriya.com/auto-industry-news/build-your-own-ford-f-150-raptor-for-only-php-5-000.html",
            "urlToImage": "https://www.autoindustriya.com/images/posts/post20467.jpg",
            "publishedAt": "2021-07-05T03:31:47Z",
            "content": "If you ever wanted to get your hands on a Ford Raptor and only have around PHP 5,000 in your pocket, you're in luck.\r\nArriving at a Lego store near you is the all-new Ford F-150 Raptor Technic. Set t… [+1517 chars]"
        },
        {
            "source": {
                "id": null,
                "name": "ScienceAlert"
            },
            "author": "Michelle Starr",
            "title": "New Orbiter Has Caught Glorious Images of Eerie Alien Auroras on Mars - ScienceAlert",
            "description": "We just got our best views yet of the eerie alien aurora on Mars.",
            "url": "https://www.sciencealert.com/the-uae-s-hope-mission-has-captured-amazing-images-of-mars-aurora",
            "urlToImage": "https://www.sciencealert.com/images/2021-07/processed/uae-mars-aurora_1024.jpg",
            "publishedAt": "2021-07-05T02:35:51Z",
            "content": "We just got our best views yet of the eerie alien aurora on Mars.\r\nThe United Arab Emirates' Hope orbiter, which arrived at the red planet earlier this year, used its ultraviolet spectrometer to catc… [+2378 chars]"
        },
        {
            "source": {
                "id": null,
                "name": "Inquirer.net"
            },
            "author": null,
            "title": "Phivolcs calls for long-term development plan around Taal Volcano - INQUIRER.net",
            "description": "Philippine news for Filipinos",
            "url": "https://www.inquirer.net/",
            "urlToImage": "https://www.inquirer.net/wp-content/uploads/2016/10/new-inq-fb-def.jpg",
            "publishedAt": "2021-07-05T02:19:00Z",
            "content": "We use cookies to ensure you get the best experience on our website. By continuing, you are agreeing to our use of cookies. To find out more, please click this link."
        },
        {
            "source": {
                "id": "google-news",
                "name": "Google News"
            },
            "author": null,
            "title": "COVID-19 threat looms in evacuation sites amid Taal unrest - CNN Philippines",
            "description": null,
            "url": "https://news.google.com/__i/rss/rd/articles/CBMiK2h0dHBzOi8vd3d3LnlvdXR1YmUuY29tL3dhdGNoP3Y9Wk5Ya01xeVI5Sk3SAQA?oc=5",
            "urlToImage": null,
            "publishedAt": "2021-07-05T02:12:43Z",
            "content": null
        }
    ]
}
